onnc/__init__.py
onnc/bench/__init__.py
onnc/bench/config.py
onnc/bench/project.py
onnc/bench/utils.py
onnc/bench/core/__init__.py
onnc/bench/core/benchmark.py
onnc/bench/core/common.py
onnc/bench/core/deployment.py
onnc/bench/core/modelpackage.py
onnc/bench/core/compiler/__init__.py
onnc/bench/core/compiler/builder.py
onnc/bench/core/compiler/nnuxe.py
onnc/bench/core/compiler/nnuxe_docker.py
onnc/bench/core/compiler/onnc_saas.py
onnc/bench/core/compiler/saas_config.py
onnc/bench/core/dataset/__init__.py
onnc/bench/core/dataset/dataset.py
onnc/bench/core/dataset/layout.py
onnc/bench/core/dataset/operation.py
onnc/bench/core/dataset/preprocessor.py
onnc/bench/core/dataset/serializer.py
onnc/bench/core/dataset/transformer.py
onnc/bench/core/evaluator/__init__.py
onnc/bench/core/model/__init__.py
onnc/bench/core/model/model.py
onnc/bench/core/model/serializer.py
onnc/bench/core/model/transformer.py
onnc/forest/__init__.py
onnc/forest/core/__init__.py
onnc/forest/core/binding_helper.py
onnc/forest/core/options.py
onnc/forest/core/runtime.py
onnc/forest/proxies/__init__.py
onnc/forest/proxies/zerorpc/__init__.py
onnc/forest/proxies/zerorpc/runtime.py
onnc/forest/proxies/zerorpc/runtime_server.py
onnc/forest/proxies/zerorpc/utils.py
onnc/forest/runtimes/__init__.py
onnc/forest/runtimes/onnx/__init__.py
onnc/forest/runtimes/onnx/runtime.py
onnc/forest/runtimes/openvino/__init__.py
onnc/forest/runtimes/openvino/runtime.py
onnc/forest/runtimes/openvino/utils.py
onnc/forest/runtimes/tensorrt/__init__.py
onnc/forest/runtimes/tensorrt/runtime.py
onnc/forest/runtimes/tensorrt/utils.py
onnc/forest/utils/__init__.py
onnc/forest/utils/load_img.py
onnc_bench-4.3.1.dist-info/METADATA
onnc_bench-4.3.1.dist-info/WHEEL
onnc_bench-4.3.1.dist-info/top_level.txt
onnc_bench-4.3.1.dist-info/RECORD
