Metadata-Version: 2.1
Name: onnc-bench
Version: 4.3.1
Summary: ONNC-bench is a Python wrapper of ONNC
Home-page: https://www.skymizer.com
Author: The Skymizer Team
Author-email: hello@skymizer.com
License: Apache License 2.0
Platform: UNKNOWN
Requires-Dist: requests
Requires-Dist: onnx
Requires-Dist: loguru
Requires-Dist: sentry-sdk
Requires-Dist: packaging
Requires-Dist: matplotlib
Requires-Dist: numpy
Requires-Dist: openvino (==2022.3.0)
Requires-Dist: read-only-attributes
Requires-Dist: click
Requires-Dist: wget
Requires-Dist: Jinja2
Requires-Dist: singledispatchmethod
Requires-Dist: msgpack-numpy
Requires-Dist: zerorpc
Requires-Dist: pydlmeta
